authnzerver/__init__.py
authnzerver/_version.py
authnzerver/authdb.py
authnzerver/autosetup.py
authnzerver/cache.py
authnzerver/confload.py
authnzerver/confvars.py
authnzerver/default-permissions-model.json
authnzerver/frontendbase.py
authnzerver/handlers.py
authnzerver/main.py
authnzerver/modtools.py
authnzerver/permissions.py
authnzerver/secrets.py
authnzerver/top-10k-passwords.txt
authnzerver/validators.py
authnzerver/actions/__init__.py
authnzerver/actions/access.py
authnzerver/actions/admin.py
authnzerver/actions/apikey.py
authnzerver/actions/email.py
authnzerver/actions/session.py
authnzerver/actions/user.py
authnzerver/example/__init__.py
authnzerver/example/basehandler.py
authnzerver/external/__init__.py
authnzerver/external/cookies/__init__.py
authnzerver/external/cookies/cookies.py
authnzerver/external/futures37/__init__.py
authnzerver/external/futures37/_base.py
authnzerver/external/futures37/process.py
authnzerver/external/futures37/thread.py
authnzerver/tests/__init__.py
authnzerver/tests/test_auth_creation.py
authnzerver/tests/test_auth_deletesessions.py
authnzerver/tests/test_auth_lockuser.py
authnzerver/tests/test_auth_login.py
authnzerver/tests/test_auth_loginlogout.py
authnzerver/tests/test_auth_passcheck.py
authnzerver/tests/test_auth_permissions.py
authnzerver/tests/test_auth_sessioninfo.py
authnzerver/tests/test_auth_timing.py
authnzerver/tests/test_confload.py
authnzerver/tests/test_permissions_anonymous.py
authnzerver/tests/test_permissions_authenticated.py
authnzerver/tests/test_permissions_limits.py
authnzerver/tests/test_permissions_locked.py
authnzerver/tests/test_permissions_staff.py
authnzerver/tests/test_permissions_superuser.py
authnzerver/tests/test_server.py
authnzerver-0.1.3.dist-info/LICENSE
authnzerver-0.1.3.dist-info/METADATA
authnzerver-0.1.3.dist-info/WHEEL
authnzerver-0.1.3.dist-info/entry_points.txt
authnzerver-0.1.3.dist-info/top_level.txt
authnzerver-0.1.3.dist-info/RECORD
