Metadata-Version: 2.1
Name: authnzerver
Version: 0.1.3
Summary: A small authentication-authorization server.
Home-page: https://github.com/waqasbhatti/authnzerver
Author: Waqas Bhatti
Author-email: waqas.afzal.bhatti@gmail.com
License: MIT
Keywords: authentication authorization tornado
Platform: UNKNOWN
Classifier: Development Status :: 3 - Alpha
Classifier: License :: OSI Approved :: MIT License
Classifier: Intended Audience :: Developers
Classifier: Topic :: Internet :: WWW/HTTP :: Session
Classifier: Operating System :: OS Independent
Classifier: Programming Language :: Python :: 3
Classifier: Programming Language :: Python :: 3 :: Only
Classifier: Programming Language :: Python :: 3.6
Classifier: Programming Language :: Python :: 3.7
Classifier: Programming Language :: Python :: 3.8
Requires-Python: >=3.6
Requires-Dist: tornado (>=5.1)
Requires-Dist: cryptography (>=2.3)
Requires-Dist: SQLAlchemy (>=1.2.11)
Requires-Dist: argon2-cffi (>=18.3.0)
Requires-Dist: fuzzywuzzy (>=0.17.0)
Requires-Dist: diskcache (>=3.0.6)
Requires-Dist: uvloop (>=0.11.0)
Requires-Dist: confusable-homoglyphs (>=3.2.0)
Requires-Dist: requests (>=2.22)
